{
    "hc_output": [
        [
            {
                "priority": "6623.0", 
                "error_code": 1, 
                "block_id": "307726", 
                "pair_role": "0", 
                "checkin_time": "2019-08-30 09:00:00", 
                "emp_distance": "0.0", 
                "start_time": "0", 
                "checkout_time": "2019-08-30 10:00:00", 
                "cus_coordinate": "10.7954833905,106.621227488", 
                "assigned": "0", 
                "emp_id": "0", 
                "request_id": "1167110176", 
                "error_desc": "NOT AVAILABLE", 
                "type": "2"
            }, 
            {
                "priority": "4420.0", 
                "error_code": 1, 
                "block_id": "307726", 
                "pair_role": "0", 
                "checkin_time": "2019-08-30 09:00:00", 
                "emp_distance": "0.0", 
                "start_time": "0", 
                "checkout_time": "2019-08-30 10:00:00", 
                "cus_coordinate": "10.7959105,106.6143647", 
                "assigned": "0", 
                "emp_id": "0", 
                "request_id": "1167164726", 
                "error_desc": "NOT AVAILABLE", 
                "type": "2"
            }, 
            {
                "priority": "6623.0", 
                "error_code": 1, 
                "block_id": "307726", 
                "pair_role": "0", 
                "checkin_time": "2019-08-30 09:00:00", 
                "emp_distance": "0.0", 
                "start_time": "0", 
                "checkout_time": "2019-08-30 10:00:00", 
                "cus_coordinate": "10.789634,106.625748", 
                "assigned": "0", 
                "emp_id": "0", 
                "request_id": "1167146146", 
                "error_desc": "NOT AVAILABLE", 
                "type": "2"
            }, 
            {
                "priority": "4420.0", 
                "error_code": 1, 
                "block_id": "307726", 
                "pair_role": "0", 
                "checkin_time": "2019-08-30 10:00:00", 
                "emp_distance": "0.0", 
                "start_time": "0", 
                "checkout_time": "2019-08-30 11:00:00", 
                "cus_coordinate": "10.7842503,106.6295624", 
                "assigned": "0", 
                "emp_id": "0", 
                "request_id": "1167171746", 
                "error_desc": "NOT AVAILABLE", 
                "type": "2"
            }, 
            {
                "priority": "4420.0", 
                "error_code": 1, 
                "block_id": "307726", 
                "pair_role": "0", 
                "checkin_time": "2019-08-30 10:00:00", 
                "emp_distance": "0.0", 
                "start_time": "0", 
                "checkout_time": "2019-08-30 11:00:00", 
                "cus_coordinate": "10.7928756459,106.633090898", 
                "assigned": "0", 
                "emp_id": "0", 
                "request_id": "1167170116", 
                "error_desc": "NOT AVAILABLE", 
                "type": "2"
            }, 
            {
                "priority": "4861.0", 
                "error_code": 0, 
                "block_id": "307726", 
                "pair_role": "main", 
                "checkin_time": "2019-08-30 10:50:00", 
                "emp_distance": "0.0", 
                "start_time": "2019-08-30 10:40:00", 
                "checkout_time": "2019-08-30 11:35:00", 
                "cus_coordinate": "10.7911039,106.6222079", 
                "assigned": "2", 
                "emp_id": "PNC14.HIEUDM1", 
                "request_id": "1167166806", 
                "error_desc": "Phan cong thanh cong, OK", 
                "type": "2"
            }, 
            {
                "priority": "4861.0", 
                "error_code": 0, 
                "block_id": "307726", 
                "pair_role": "main", 
                "checkin_time": "2019-08-30 10:50:00", 
                "emp_distance": "0.0", 
                "start_time": "2019-08-30 10:40:00", 
                "checkout_time": "2019-08-30 11:35:00", 
                "cus_coordinate": "10.7987452,106.613441", 
                "assigned": "2", 
                "emp_id": "PNC14.TAMNNC", 
                "request_id": "1167151866", 
                "error_desc": "Phan cong thanh cong, OK", 
                "type": "2"
            }, 
            {
                "priority": "3907.0", 
                "error_code": 0, 
                "block_id": "307726", 
                "pair_role": "main", 
                "checkin_time": "2019-08-30 10:50:00", 
                "emp_distance": "0.0", 
                "start_time": "2019-08-30 10:40:00", 
                "checkout_time": "2019-08-30 11:50:00", 
                "cus_coordinate": "10.7915477,106.6324346", 
                "assigned": "2", 
                "emp_id": "PNC14.TANVD", 
                "request_id": "1071680796", 
                "error_desc": "Phan cong thanh cong, OK", 
                "type": "1"
            }
        ]
    ], 
    "input": [
        {
            "tasks": [
                {
                    "time_end": "2019-08-31 10:00:00", 
                    "cus_coordinate": "10.793296,106.616416", 
                    "sub_type_1_desc": "Bao tri logic", 
                    "vip": 3, 
                    "reason_out_case_desc": "nha tuyen hen lai", 
                    "sub_type_2": 47, 
                    "reason_out_case_type": 99, 
                    "vip_desc": "Khac", 
                    "impact": 3, 
                    "sub_type_1": 2, 
                    "time_start": "2019-08-31 09:00:00", 
                    "manual_priority": 0, 
                    "request_status": 0, 
                    "number_emp_needed": 1, 
                    "type": 2, 
                    "request_created_at": "2019-08-29 08:21:44", 
                    "vip2": 8, 
                    "appointmentdate_emp": "", 
                    "appointmentdate": "2019-08-31 10:00:00", 
                    "releaseoutdate": "2019-08-29 11:22:27", 
                    "box": 0, 
                    "date_confirmed": 1, 
                    "type_desc": "Bao tri", 
                    "emp_speciallized": "", 
                    "request_id": 1167069276, 
                    "emp_reserved": "", 
                    "sub_type_2_desc": "Ket noi duoc wifi nhung khong truy cap duoc hoac truy cap rat cham"
                }, 
                {
                    "time_end": "2019-08-30 10:00:00", 
                    "cus_coordinate": "10.795483390487123,106.62122748792173", 
                    "sub_type_1_desc": "Bao tri logic", 
                    "vip": 3, 
                    "reason_out_case_desc": "Xu ly viec rieng", 
                    "sub_type_2": 23, 
                    "reason_out_case_type": 1, 
                    "vip_desc": "Khac", 
                    "impact": 3, 
                    "sub_type_1": 2, 
                    "time_start": "2019-08-30 09:00:00", 
                    "manual_priority": 0, 
                    "request_status": 0, 
                    "number_emp_needed": 1, 
                    "type": 2, 
                    "request_created_at": "2019-08-29 14:10:56", 
                    "vip2": 8, 
                    "appointmentdate_emp": "", 
                    "appointmentdate": "2019-08-30 09:00:00", 
                    "releaseoutdate": "2019-08-30 08:10:26", 
                    "box": 0, 
                    "date_confirmed": 1, 
                    "type_desc": "Bao tri", 
                    "emp_speciallized": "", 
                    "request_id": 1167110176, 
                    "emp_reserved": "", 
                    "sub_type_2_desc": "Bao tri theo yeu cau KH"
                }, 
                {
                    "time_end": "2019-08-30 17:00:00", 
                    "cus_coordinate": "10.7987452,106.613441", 
                    "sub_type_1_desc": "Bao tri logic", 
                    "vip": 3, 
                    "reason_out_case_desc": "", 
                    "sub_type_2": 48, 
                    "reason_out_case_type": -1, 
                    "vip_desc": "Khac", 
                    "impact": 1, 
                    "sub_type_1": 2, 
                    "time_start": "2019-08-30 16:00:00", 
                    "manual_priority": 0, 
                    "request_status": 0, 
                    "number_emp_needed": 1, 
                    "type": 2, 
                    "request_created_at": "2019-08-29 21:27:41", 
                    "vip2": 8, 
                    "appointmentdate_emp": "2019-08-30 17:00:00", 
                    "appointmentdate": "2019-08-30 17:00:00", 
                    "releaseoutdate": "", 
                    "box": 0, 
                    "date_confirmed": 1, 
                    "type_desc": "Bao tri", 
                    "emp_speciallized": "", 
                    "request_id": 1167151866, 
                    "emp_reserved": "", 
                    "sub_type_2_desc": "Truy cap Internet Quoc Te chap chon"
                }, 
                {
                    "time_end": "2019-08-30 17:00:00", 
                    "cus_coordinate": "10.7911039,106.6222079", 
                    "sub_type_1_desc": "Bao tri logic", 
                    "vip": 3, 
                    "reason_out_case_desc": "", 
                    "sub_type_2": 59, 
                    "reason_out_case_type": -1, 
                    "vip_desc": "Khac", 
                    "impact": 1, 
                    "sub_type_1": 2, 
                    "time_start": "2019-08-30 16:00:00", 
                    "manual_priority": 0, 
                    "request_status": 0, 
                    "number_emp_needed": 1, 
                    "type": 2, 
                    "request_created_at": "2019-08-30 08:58:58", 
                    "vip2": 8, 
                    "appointmentdate_emp": "2019-08-30 17:00:00", 
                    "appointmentdate": "2019-08-30 17:00:00", 
                    "releaseoutdate": "", 
                    "box": 0, 
                    "date_confirmed": 1, 
                    "type_desc": "Bao tri", 
                    "emp_speciallized": "", 
                    "request_id": 1167166806, 
                    "emp_reserved": "", 
                    "sub_type_2_desc": "KH khong hop tac"
                }, 
                {
                    "time_end": "2019-08-30 10:00:00", 
                    "cus_coordinate": "10.7959105,106.6143647", 
                    "sub_type_1_desc": "Bao tri logic", 
                    "vip": 3, 
                    "reason_out_case_desc": "", 
                    "sub_type_2": 11, 
                    "reason_out_case_type": -1, 
                    "vip_desc": "Khac", 
                    "impact": 0, 
                    "sub_type_1": 2, 
                    "time_start": "2019-08-30 09:00:00", 
                    "manual_priority": 0, 
                    "request_status": 0, 
                    "number_emp_needed": 1, 
                    "type": 2, 
                    "request_created_at": "2019-08-30 08:42:54", 
                    "vip2": 8, 
                    "appointmentdate_emp": "", 
                    "appointmentdate": "2019-08-30 10:00:00", 
                    "releaseoutdate": "", 
                    "box": 0, 
                    "date_confirmed": 1, 
                    "type_desc": "Bao tri", 
                    "emp_speciallized": "", 
                    "request_id": 1167164726, 
                    "emp_reserved": "", 
                    "sub_type_2_desc": "KH mua doi thiet b\u1ecb"
                }, 
                {
                    "time_end": "2019-08-30 10:00:00", 
                    "cus_coordinate": "10.789634,106.625748", 
                    "sub_type_1_desc": "Bao tri logic", 
                    "vip": 3, 
                    "reason_out_case_desc": "", 
                    "sub_type_2": 104, 
                    "reason_out_case_type": -1, 
                    "vip_desc": "Khac", 
                    "impact": 3, 
                    "sub_type_1": 2, 
                    "time_start": "2019-08-30 09:00:00", 
                    "manual_priority": 0, 
                    "request_status": 0, 
                    "number_emp_needed": 1, 
                    "type": 2, 
                    "request_created_at": "2019-08-29 20:11:29", 
                    "vip2": 8, 
                    "appointmentdate_emp": "", 
                    "appointmentdate": "2019-08-30 09:00:00", 
                    "releaseoutdate": "", 
                    "box": 0, 
                    "date_confirmed": 1, 
                    "type_desc": "Bao tri", 
                    "emp_speciallized": "PNC14.ANHTT7,PNC14.ANHTT7,PNC14.DANHNT3,PNC14.DANHNT3,PNC14.DUNGBD,PNC14.DUNGBD,PNC14.HAUPC,PNC14.HAUPC,PNC14.HENTT,PNC14.TAMNNC,PNC14.TAMNNC", 
                    "request_id": 1167146146, 
                    "emp_reserved": "", 
                    "sub_type_2_desc": "Loi thiet bi"
                }, 
                {
                    "time_end": "2019-08-31 09:00:00", 
                    "cus_coordinate": "10.7886291,106.6261501", 
                    "sub_type_1_desc": "Bao tri logic", 
                    "vip": 3, 
                    "reason_out_case_desc": "", 
                    "sub_type_2": 51, 
                    "reason_out_case_type": -1, 
                    "vip_desc": "Khac", 
                    "impact": 0, 
                    "sub_type_1": 2, 
                    "time_start": "2019-08-31 08:00:00", 
                    "manual_priority": 0, 
                    "request_status": 0, 
                    "number_emp_needed": 1, 
                    "type": 2, 
                    "request_created_at": "2019-08-29 20:00:27", 
                    "vip2": 8, 
                    "appointmentdate_emp": "", 
                    "appointmentdate": "2019-08-31 09:00:00", 
                    "releaseoutdate": "", 
                    "box": 0, 
                    "date_confirmed": 1, 
                    "type_desc": "Bao tri", 
                    "emp_speciallized": "", 
                    "request_id": 1167145316, 
                    "emp_reserved": "", 
                    "sub_type_2_desc": "Tin hieu tot khong IP wan - Mat cau hinh"
                }, 
                {
                    "time_end": "2019-08-31 10:00:00", 
                    "cus_coordinate": "10.7932411,106.6314271", 
                    "sub_type_1_desc": "Trien khai indoor outdoor", 
                    "vip": 3, 
                    "reason_out_case_desc": "", 
                    "sub_type_2": 1, 
                    "reason_out_case_type": -1, 
                    "vip_desc": "Khac", 
                    "impact": 0, 
                    "sub_type_1": 3, 
                    "time_start": "2019-08-31 08:00:00", 
                    "manual_priority": 0, 
                    "request_status": 0, 
                    "number_emp_needed": 1, 
                    "type": 1, 
                    "request_created_at": "2019-08-29 10:09:07", 
                    "vip2": 8, 
                    "appointmentdate_emp": "", 
                    "appointmentdate": "2019-08-31 10:00:00", 
                    "releaseoutdate": "", 
                    "box": 0, 
                    "date_confirmed": 1, 
                    "type_desc": "Trien khai", 
                    "emp_speciallized": "", 
                    "request_id": 1071668596, 
                    "emp_reserved": "", 
                    "sub_type_2_desc": "Chuyen dia diem"
                }, 
                {
                    "time_end": "2019-08-30 11:00:00", 
                    "cus_coordinate": "10.7842503,106.6295624", 
                    "sub_type_1_desc": "Bao tri logic", 
                    "vip": 3, 
                    "reason_out_case_desc": "", 
                    "sub_type_2": 38, 
                    "reason_out_case_type": -1, 
                    "vip_desc": "Khac", 
                    "impact": 0, 
                    "sub_type_1": 2, 
                    "time_start": "2019-08-30 10:00:00", 
                    "manual_priority": 0, 
                    "request_status": 0, 
                    "number_emp_needed": 1, 
                    "type": 2, 
                    "request_created_at": "2019-08-30 09:32:23", 
                    "vip2": 8, 
                    "appointmentdate_emp": "", 
                    "appointmentdate": "2019-08-30 11:00:00", 
                    "releaseoutdate": "", 
                    "box": 0, 
                    "date_confirmed": 1, 
                    "type_desc": "Bao tri", 
                    "emp_speciallized": "", 
                    "request_id": 1167171746, 
                    "emp_reserved": "", 
                    "sub_type_2_desc": "Khong load duoc portal"
                }, 
                {
                    "time_end": "2019-08-30 11:00:00", 
                    "cus_coordinate": "10.792875645920159,106.6330908983946", 
                    "sub_type_1_desc": "Bao tri vat ly", 
                    "vip": 3, 
                    "reason_out_case_desc": "", 
                    "sub_type_2": 4, 
                    "reason_out_case_type": -1, 
                    "vip_desc": "Khac", 
                    "impact": 0, 
                    "sub_type_1": 1, 
                    "time_start": "2019-08-30 10:00:00", 
                    "manual_priority": 0, 
                    "request_status": 0, 
                    "number_emp_needed": 1, 
                    "type": 2, 
                    "request_created_at": "2019-08-30 09:20:30", 
                    "vip2": 8, 
                    "appointmentdate_emp": "", 
                    "appointmentdate": "2019-08-30 11:00:00", 
                    "releaseoutdate": "", 
                    "box": 0, 
                    "date_confirmed": 1, 
                    "type_desc": "Bao tri", 
                    "emp_speciallized": "", 
                    "request_id": 1167170116, 
                    "emp_reserved": "", 
                    "sub_type_2_desc": "Khong co tin hieu"
                }, 
                {
                    "time_end": "2019-08-30 17:30:00", 
                    "cus_coordinate": "10.7915477,106.6324346", 
                    "sub_type_1_desc": "Trien khai Indoor", 
                    "vip": 3, 
                    "reason_out_case_desc": "", 
                    "sub_type_2": 16, 
                    "reason_out_case_type": -1, 
                    "vip_desc": "Khac", 
                    "impact": 0, 
                    "sub_type_1": 4, 
                    "time_start": "2019-08-30 15:30:00", 
                    "manual_priority": 0, 
                    "request_status": 0, 
                    "number_emp_needed": 1, 
                    "type": 1, 
                    "request_created_at": "2019-08-29 14:21:58", 
                    "vip2": 8, 
                    "appointmentdate_emp": "", 
                    "appointmentdate": "2019-08-30 17:30:00", 
                    "releaseoutdate": "", 
                    "box": 0, 
                    "date_confirmed": 1, 
                    "type_desc": "Trien khai", 
                    "emp_speciallized": "PNC14.ANHTT7,PNC14.DANHNT3,PNC14.TAMNNC,PNC14.TANVD", 
                    "request_id": 1071680796, 
                    "emp_reserved": "", 
                    "sub_type_2_desc": "Swap ha tang"
                }, 
                {
                    "time_end": "2019-08-31 16:00:00", 
                    "cus_coordinate": "10.79351023,106.62308297", 
                    "sub_type_1_desc": "Bao tri logic", 
                    "vip": 3, 
                    "reason_out_case_desc": "", 
                    "sub_type_2": 11, 
                    "reason_out_case_type": -1, 
                    "vip_desc": "Khac", 
                    "impact": 0, 
                    "sub_type_1": 2, 
                    "time_start": "2019-08-31 15:00:00", 
                    "manual_priority": 0, 
                    "request_status": 0, 
                    "number_emp_needed": 1, 
                    "type": 2, 
                    "request_created_at": "2019-08-26 17:01:44", 
                    "vip2": 8, 
                    "appointmentdate_emp": "", 
                    "appointmentdate": "2019-08-31 16:00:00", 
                    "releaseoutdate": "", 
                    "box": 0, 
                    "date_confirmed": 1, 
                    "type_desc": "Bao tri", 
                    "emp_speciallized": "", 
                    "request_id": 1166847156, 
                    "emp_reserved": "", 
                    "sub_type_2_desc": "KH mua doi thiet b\u1ecb"
                }, 
                {
                    "time_end": "2019-08-31 09:00:00", 
                    "cus_coordinate": "10.790371294022771,106.62460774183273", 
                    "sub_type_1_desc": "Bao tri logic", 
                    "vip": 3, 
                    "reason_out_case_desc": "", 
                    "sub_type_2": 23, 
                    "reason_out_case_type": -1, 
                    "vip_desc": "Khac", 
                    "impact": 1, 
                    "sub_type_1": 2, 
                    "time_start": "2019-08-31 08:00:00", 
                    "manual_priority": 0, 
                    "request_status": 0, 
                    "number_emp_needed": 1, 
                    "type": 2, 
                    "request_created_at": "2019-08-27 15:35:32", 
                    "vip2": 8, 
                    "appointmentdate_emp": "", 
                    "appointmentdate": "2019-08-31 09:00:00", 
                    "releaseoutdate": "", 
                    "box": 0, 
                    "date_confirmed": 1, 
                    "type_desc": "Bao tri", 
                    "emp_speciallized": "PNC14.ANHTT7,PNC14.ANHTT7,PNC14.DANHNT3,PNC14.DANHNT3,PNC14.DUNGBD,PNC14.DUNGBD,PNC14.HAUPC,PNC14.HAUPC,PNC14.HENTT,PNC14.TAMNNC,PNC14.TAMNNC", 
                    "request_id": 1166933316, 
                    "emp_reserved": "", 
                    "sub_type_2_desc": "Bao tri theo yeu cau KH"
                }, 
                {
                    "time_end": "2019-08-31 09:00:00", 
                    "cus_coordinate": "10.7886779,106.624188", 
                    "sub_type_1_desc": "Bao tri logic", 
                    "vip": 3, 
                    "reason_out_case_desc": "", 
                    "sub_type_2": 45, 
                    "reason_out_case_type": -1, 
                    "vip_desc": "Khac", 
                    "impact": 0, 
                    "sub_type_1": 2, 
                    "time_start": "2019-08-31 08:00:00", 
                    "manual_priority": 0, 
                    "request_status": 0, 
                    "number_emp_needed": 1, 
                    "type": 2, 
                    "request_created_at": "2019-08-29 17:55:05", 
                    "vip2": 8, 
                    "appointmentdate_emp": "", 
                    "appointmentdate": "2019-08-31 09:00:00", 
                    "releaseoutdate": "", 
                    "box": 0, 
                    "date_confirmed": 1, 
                    "type_desc": "Bao tri", 
                    "emp_speciallized": "PNC14.ANHTT7,PNC14.ANHTT7,PNC14.DANHNT3,PNC14.HOANGTK,PNC14.MANTDM,PNC14.MANTDM,PNC14.TAMNNC,PNC14.TAMNNC,PNC14.TANVD,PNC14.TANVD", 
                    "request_id": 1167134726, 
                    "emp_reserved": "", 
                    "sub_type_2_desc": "Khong ket noi duoc wifi"
                }, 
                {
                    "time_end": "2019-08-31 09:00:00", 
                    "cus_coordinate": "10.7840215,106.6267517", 
                    "sub_type_1_desc": "Bao tri logic", 
                    "vip": 3, 
                    "reason_out_case_desc": "nha tuyen hen lai", 
                    "sub_type_2": 40, 
                    "reason_out_case_type": 99, 
                    "vip_desc": "Khac", 
                    "impact": 0, 
                    "sub_type_1": 2, 
                    "time_start": "2019-08-31 09:00:00", 
                    "manual_priority": 0, 
                    "request_status": 0, 
                    "number_emp_needed": 1, 
                    "type": 2, 
                    "request_created_at": "2019-08-24 17:35:21", 
                    "vip2": 8, 
                    "appointmentdate_emp": "", 
                    "appointmentdate": "2019-08-31 09:00:00", 
                    "releaseoutdate": "2019-08-27 08:30:12", 
                    "box": 0, 
                    "date_confirmed": 1, 
                    "type_desc": "Bao tri", 
                    "emp_speciallized": "", 
                    "request_id": 1166674036, 
                    "emp_reserved": "", 
                    "sub_type_2_desc": "Loi ket noi Box va TV"
                }
            ], 
            "block_id": 307726, 
            "block_gray": "", 
            "block_name": "Q.Tan Phu-002", 
            "block_distance": 30000.0, 
            "res_time": "2019-08-30 09:44:03", 
            "resources": [
                {
                    "available": "09:43 - 18:30", 
                    "request_impossible": "", 
                    "type_desc": "NVKT", 
                    "emp_coordinate": "10.8063211952,106.637485027", 
                    "rank": "B", 
                    "emp_status": 1, 
                    "emp_level": 1, 
                    "emp_assigned": 1, 
                    "emp_id": "PNC14.HOANGTK", 
                    "type": 1
                }, 
                {
                    "available": "10:40 - 18:30", 
                    "request_impossible": "", 
                    "type_desc": "NVKT", 
                    "emp_coordinate": "10.7898882,106.6324792", 
                    "rank": "B", 
                    "emp_status": 1, 
                    "emp_level": 3, 
                    "emp_assigned": 1, 
                    "emp_id": "PNC14.TANVD", 
                    "type": 1
                }, 
                {
                    "available": "09:43 - 18:30", 
                    "request_impossible": "", 
                    "type_desc": "KTV", 
                    "emp_coordinate": "10.7831555,106.6208502", 
                    "rank": "B", 
                    "emp_status": 1, 
                    "emp_level": 2, 
                    "emp_assigned": 1, 
                    "emp_id": "PNC14.TAMNNC", 
                    "type": 2
                }, 
                {
                    "available": "09:43 - 18:30", 
                    "request_impossible": "", 
                    "type_desc": "KTV", 
                    "emp_coordinate": "10.758210,106.645333", 
                    "rank": "B", 
                    "emp_status": 1, 
                    "emp_level": 1, 
                    "emp_assigned": 0, 
                    "emp_id": "PNC14.ANHTT7", 
                    "type": 2
                }, 
                {
                    "available": "09:43 - 18:30", 
                    "request_impossible": "", 
                    "type_desc": "NVKT", 
                    "emp_coordinate": "10.7871783,106.6302182", 
                    "rank": "A", 
                    "emp_status": 1, 
                    "emp_level": 4, 
                    "emp_assigned": 3, 
                    "emp_id": "PNC14.DUNGBD", 
                    "type": 1
                }, 
                {
                    "available": "09:43 - 18:30", 
                    "request_impossible": "", 
                    "type_desc": "KTV", 
                    "emp_coordinate": "10.7893199,106.6233357", 
                    "rank": "B", 
                    "emp_status": 1, 
                    "emp_level": 1, 
                    "emp_assigned": 1, 
                    "emp_id": "PNC14.HIEUDM1", 
                    "type": 2
                }, 
                {
                    "available": "09:43 - 18:30", 
                    "request_impossible": "", 
                    "type_desc": "NVKT", 
                    "emp_coordinate": "10.7993103,106.6188998", 
                    "rank": "A", 
                    "emp_status": 1, 
                    "emp_level": 5, 
                    "emp_assigned": 1, 
                    "emp_id": "PNC14.PHATTT", 
                    "type": 1
                }, 
                {
                    "available": "10:40 - 18:30", 
                    "request_impossible": "", 
                    "type_desc": "NVKT", 
                    "emp_coordinate": "10.7859205,106.6276102", 
                    "rank": "B", 
                    "emp_status": 1, 
                    "emp_level": 3, 
                    "emp_assigned": 1, 
                    "emp_id": "PNC14.MANTDM", 
                    "type": 1
                }, 
                {
                    "available": "11:10 - 18:30", 
                    "request_impossible": "", 
                    "type_desc": "NVKT", 
                    "emp_coordinate": "10.7897616,106.6332549", 
                    "rank": "B", 
                    "emp_status": 1, 
                    "emp_level": 3, 
                    "emp_assigned": 1, 
                    "emp_id": "PNC14.LUUTV", 
                    "type": 1
                }, 
                {
                    "available": "09:43 - 18:30", 
                    "request_impossible": "", 
                    "type_desc": "NVKT", 
                    "emp_coordinate": "10.7951228,106.629037", 
                    "rank": "B", 
                    "emp_status": 1, 
                    "emp_level": 1, 
                    "emp_assigned": 1, 
                    "emp_id": "PNC14.HAUPC", 
                    "type": 1
                }, 
                {
                    "available": "09:43 - 18:30", 
                    "request_impossible": "", 
                    "type_desc": "NVKT", 
                    "emp_coordinate": "10.7980095,106.584658", 
                    "rank": "B", 
                    "emp_status": 1, 
                    "emp_level": 1, 
                    "emp_assigned": 1, 
                    "emp_id": "PNC14.HENTT", 
                    "type": 1
                }
            ]
        }
    ], 
    "version": "production_20190827_2033", 
    "res_time": "20190830_094403", 
    "glpk_output": []
}